calconstruccion/__init__.py
calconstruccion/database.xlsx
calconstruccion/main.py
calconstruccion/utils/__init__.py
calconstruccion/utils/excelfile.py
calconstruccion/utils/importar.py
calconstruccion-0.1.0.dist-info/WHEEL
calconstruccion-0.1.0.dist-info/METADATA
calconstruccion-0.1.0.dist-info/RECORD
