Metadata-Version: 2.1
Name: calconstruccion
Version: 0.1.0
Summary: 
Author: Stefy0408
Author-email: caroarevaldivieso@gmail.com
Requires-Python: >=3.9,<4.0
Classifier: Programming Language :: Python :: 3
Classifier: Programming Language :: Python :: 3.10
Classifier: Programming Language :: Python :: 3.9
Requires-Dist: openpyxl (>=3.0.10,<4.0.0)
Requires-Dist: pandas (>=1.4.3,<2.0.0)
